TurkishPreprocessor/Preprocessor.py
TurkishPreprocessor/__init__.py
TurkishPreprocessor/Turkish_Lemmatizer/__init__.py
TurkishPreprocessor/Turkish_Lemmatizer/lemmatizer.py
TurkishPreprocessor/Turkish_Lemmatizer/revisedDict.pkl
TurkishPreprocessor/Turkish_Lemmatizer/trainLexicon.py
TurkishPreprocessor-0.0.4.data/data/config/revisedDict.pkl
TurkishPreprocessor-0.0.4.dist-info/LICENSE
TurkishPreprocessor-0.0.4.dist-info/METADATA
TurkishPreprocessor-0.0.4.dist-info/WHEEL
TurkishPreprocessor-0.0.4.dist-info/top_level.txt
TurkishPreprocessor-0.0.4.dist-info/RECORD
