Metadata-Version: 2.1
Name: TurkishPreprocessor
Version: 0.0.4
Summary: A Turkish Preprocessor for NLP
Home-page: https://github.com/yusufani/TurkishPreprocessor
Author: Yusuf ANI
Author-email: yusufani8@gmail.com
License: UNKNOWN
Platform: UNKNOWN
Classifier: Programming Language :: Python :: 3
Classifier: License :: OSI Approved :: MIT License
Classifier: Operating System :: OS Independent
